gitready/__init__.py
gitready/__main__.py
gitready-0.1.1.data/data/files/CONTRIBUTING.md
gitready-0.1.1.data/data/files/MANIFEST.in
gitready-0.1.1.data/data/files/Makefile
gitready-0.1.1.data/data/files/README.md
gitready-0.1.1.data/data/files/gitignore
gitready-0.1.1.data/data/files/init_py
gitready-0.1.1.data/data/files/main_py
gitready-0.1.1.data/data/files/requirements.txt
gitready-0.1.1.data/data/files/setup_cfg
gitready-0.1.1.data/data/files/setup_py
gitready-0.1.1.data/data/files/tests_init_py
gitready-0.1.1.data/data/files/tox.ini
gitready-0.1.1.data/data/files/travis.yml
gitready-0.1.1.data/data/files/licenses/apache2
gitready-0.1.1.data/data/files/licenses/bsd
gitready-0.1.1.data/data/files/licenses/gplv3
gitready-0.1.1.data/data/files/licenses/mit
gitready-0.1.1.data/data/files/licenses/mozilla
gitready-0.1.1.data/data/files/notices/apache2
gitready-0.1.1.dist-info/LICENSE
gitready-0.1.1.dist-info/METADATA
gitready-0.1.1.dist-info/WHEEL
gitready-0.1.1.dist-info/entry_points.txt
gitready-0.1.1.dist-info/top_level.txt
gitready-0.1.1.dist-info/RECORD
